MANIFEST.in
README.rst
setup.py
goless/__init__.py
goless/backends.py
goless/channels.py
goless/compat.py
goless/selecting.py
goless.egg-info/PKG-INFO
goless.egg-info/SOURCES.txt
goless.egg-info/dependency_links.txt
goless.egg-info/requires.txt
goless.egg-info/top_level.txt