Metadata-Version: 1.1
Name: goless
Version: 0.7.2
Summary: Provides a Go-like concurrent programming style in Python.
Home-page: https://github.com/rgalanakis/goless
Author: Rob Galanakis
Author-email: rob.galanakis@gmail.com
License: Apache
Keywords: tasklet stackless go concurrent threading async gevent go golang
Platform: UNKNOWN
Classifier: Development Status :: 4 - Beta
Classifier: Intended Audience :: Developers
Classifier: License :: OSI Approved :: Apache Software License
Classifier: Natural Language :: English
Classifier: Operating System :: OS Independent
Classifier: Programming Language :: Python
Classifier: Programming Language :: Python :: 2
Classifier: Programming Language :: Python :: 2.6
Classifier: Programming Language :: Python :: 2.7
Classifier: Programming Language :: Python :: 3
Classifier: Programming Language :: Python :: 3.3
Classifier: Programming Language :: Python :: 3.4
